{
  "Luanda": {
    "Cacuaco": {
      "Cacuaco": [],
      "Kikolo": []
    },
    "Cazenga": {
      "Cazenga": [],
      "Kima Kieza": []
    },
    "Viana": {},
    "Belas": {
      "Barra do Cuanza": [],
      "Cabolombo": [],
      "Ramiros": []
    },
    "Kilamba Kiaxi": {
      "Golfe": [],
      "Nova Vida": []
    },
    "Talatona": {
      "Talatona": [],
      "Benfica": []
    },
    "Kilamba": {
      "Kilamba": [],
      "Vila Flor": []
    },
    "Camama": {},
    "Ingombota": {},
    "Sambizanga": {},
    "Rangel": {},
    "Maianga": {},
    "Samba": {},
    "Mussulo": {},
    "Hoji Ya Henda": {},
    "Mulenvos": {}
  }
}
